django_gtm-0.1.dist-info/DESCRIPTION.rst
django_gtm-0.1.dist-info/METADATA
django_gtm-0.1.dist-info/RECORD
django_gtm-0.1.dist-info/WHEEL
django_gtm-0.1.dist-info/metadata.json
django_gtm-0.1.dist-info/top_level.txt
gtm/__init__.py
gtm/admin.py
gtm/apps.py
gtm/models.py
gtm/tests.py
gtm/migrations/0001_initial.py
gtm/migrations/__init__.py
gtm/templates/gtm/gtm.html
gtm/templates/gtm/gtm_body.html
gtm/templates/gtm/gtm_head.html
gtm/templatetags/__init__.py
gtm/templatetags/gtm_tags.py
